rfc3986/__init__.py
rfc3986/_mixin.py
rfc3986/abnf_regexp.py
rfc3986/api.py
rfc3986/builder.py
rfc3986/compat.py
rfc3986/exceptions.py
rfc3986/iri.py
rfc3986/misc.py
rfc3986/normalizers.py
rfc3986/parseresult.py
rfc3986/uri.py
rfc3986/validators.py
rfc3986-1.3.1.dist-info/AUTHORS.rst
rfc3986-1.3.1.dist-info/LICENSE
rfc3986-1.3.1.dist-info/METADATA
rfc3986-1.3.1.dist-info/WHEEL
rfc3986-1.3.1.dist-info/top_level.txt
rfc3986-1.3.1.dist-info/RECORD
