Metadata-Version: 2.1
Name: rfc3986
Version: 1.3.1
Summary: Validating URI References per RFC 3986
Home-page: http://rfc3986.readthedocs.io
Author: Ian Stapleton Cordasco
Author-email: graffatcolmingov@gmail.com
License: Apache 2.0
Platform: UNKNOWN
Classifier: Development Status :: 5 - Production/Stable
Classifier: Intended Audience :: Developers
Classifier: Natural Language :: English
Classifier: License :: OSI Approved :: Apache Software License
Classifier: Programming Language :: Python
Classifier: Programming Language :: Python :: 2.7
Classifier: Programming Language :: Python :: 3
Classifier: Programming Language :: Python :: 3.4
Classifier: Programming Language :: Python :: 3.5
Classifier: Programming Language :: Python :: 3.6
Classifier: Programming Language :: Python :: 3.7
Provides-Extra: idna2008
Requires-Dist: idna ; extra == 'idna2008'
